{
  "date": "2018-04-08",
  "sunrise": "06:58",
  "sunset": "18:24",
  "minTemp": 17.6,
  "maxTemp": 23.2,
  "hourly": [
    {
      "time": "3",
      "weatherCode": "PARTLY_CLOUDY",
      "temp": 18.2,
      "humidity": 89,
      "dewPoint": 16.4,
      "pressure": 1017.4,
      "pressureChange": "",
      "windDirectionCode": "ESE",
      "windSpeed": 2.1,
      "visibility": "---",
      "discomfortIndex": 64
    },
    {
      "time": "6",
      "weatherCode": "CLEAR",
      "temp": 18.2,
      "humidity": 90,
      "dewPoint": 16.5,
      "pressure": 1017.1,
      "pressureChange": "-0.3",
      "windDirectionCode": "ENE",
      "windSpeed": 2.5,
      "visibility": "---",
      "discomfortIndex": 64
    },
    {
      "time": "9",
      "weatherCode": "PARTLY_CLOUDY",
      "temp": 19.3,
      "humidity": 88,
      "dewPoint": 17.3,
      "pressure": 1018.8,
      "pressureChange": "+1.7",
      "windDirectionCode": "NNE",
      "windSpeed": 1.9,
      "visibility": "---",
      "discomfortIndex": 66
    },
    {
      "time": "12",
      "weatherCode": "CLOUDY",
      "temp": 23.2,
      "humidity": 63,
      "dewPoint": 15.9,
      "pressure": 1018.6,
      "pressureChange": "-0.2",
      "windDirectionCode": "ENE",
      "windSpeed": 2.3,
      "visibility": "---",
      "discomfortIndex": 71
    },
    {
      "time": "15",
      "weatherCode": "CLOUDY",
      "temp": 22.2,
      "humidity": 74,
      "dewPoint": 17.3,
      "pressure": 1017.4,
      "pressureChange": "-1.2",
      "windDirectionCode": "ESE",
      "windSpeed": 5.0,
      "visibility": "---",
      "discomfortIndex": 70
    },
    {
      "time": "18",
      "weatherCode": "CLOUDY",
      "temp": 20.7,
      "humidity": 80,
      "dewPoint": 17.1,
      "pressure": 1016.7,
      "pressureChange": "-0.7",
      "windDirectionCode": "E",
      "windSpeed": 3.8,
      "visibility": "---",
      "discomfortIndex": 68
    },
    {
      "time": "21",
      "weatherCode": "CLOUDY",
      "temp": 20.0,
      "humidity": 87,
      "dewPoint": 17.9,
      "pressure": 1017.8,
      "pressureChange": "+1.1",
      "windDirectionCode": "E",
      "windSpeed": 1.4,
      "visibility": "---",
      "discomfortIndex": 67
    },
    {
      "time": "24",
      "weatherCode": "CLOUDY",
      "temp": 19.0,
      "humidity": 93,
      "dewPoint": 17.8,
      "pressure": 1017.1,
      "pressureChange": "-0.7",
      "windDirectionCode": "N",
      "windSpeed": 1.3,
      "visibility": "---",
      "discomfortIndex": 66
    }
  ]
}
